asciititle/__init__.py
asciititle/asciititle.py
asciititle/custom_fonts.py
asciititle/title.py
my_ascii_lib/__init__.py
my_ascii_lib/ascii.py
my_ascii_lib/font_loader.py
my_ascii_lib/fonts/blurvision.json
asciititle-0.2.0.dist-info/LICENSE
asciititle-0.2.0.dist-info/METADATA
asciititle-0.2.0.dist-info/WHEEL
asciititle-0.2.0.dist-info/top_level.txt
asciititle-0.2.0.dist-info/RECORD
