Metadata-Version: 2.1
Name: asciititle
Version: 0.2.0
Summary: A library for generating ASCII art with custom fonts
Home-page: https://github.com/devvyyxyz/asciititle
Author: devvyyxyz
Author-email: info@devvyy.xyz
Classifier: Programming Language :: Python :: 3
Classifier: License :: OSI Approved :: MIT License
Classifier: Operating System :: OS Independent
Requires-Python: >=3.6
License-File: LICENSE
